elemental_cms-2.0.6.dist-info/licenses/LICENSE
elementalcms/__init__.py
elementalcms/core/__init__.py
elementalcms/core/elementalcontext.py
elementalcms/core/flaskcontext.py
elementalcms/core/mongodbcontext.py
elementalcms/extends/__init__.py
elementalcms/extends/actionsdecorators.py
elementalcms/extends/actionsmapper.py
elementalcms/extends/applet.py
elementalcms/extends/controller.py
elementalcms/management/__init__.py
elementalcms/management/cli.py
elementalcms/management/globaldeps.py
elementalcms/management/media.py
elementalcms/management/pages.py
elementalcms/management/snippets.py
elementalcms/management/static.py
elementalcms/management/globaldepscommands/__init__.py
elementalcms/management/globaldepscommands/create.py
elementalcms/management/globaldepscommands/list.py
elementalcms/management/globaldepscommands/pull.py
elementalcms/management/globaldepscommands/push.py
elementalcms/management/globaldepscommands/remove.py
elementalcms/management/mediacommands/__init__.py
elementalcms/management/mediacommands/delete.py
elementalcms/management/mediacommands/list.py
elementalcms/management/mediacommands/pull.py
elementalcms/management/mediacommands/push.py
elementalcms/management/pagescommands/__init__.py
elementalcms/management/pagescommands/create.py
elementalcms/management/pagescommands/diff.py
elementalcms/management/pagescommands/list.py
elementalcms/management/pagescommands/publish.py
elementalcms/management/pagescommands/pull.py
elementalcms/management/pagescommands/push.py
elementalcms/management/pagescommands/remove.py
elementalcms/management/pagescommands/unpublish.py
elementalcms/management/snippetscommands/__init__.py
elementalcms/management/snippetscommands/create.py
elementalcms/management/snippetscommands/diff.py
elementalcms/management/snippetscommands/list.py
elementalcms/management/snippetscommands/pull.py
elementalcms/management/snippetscommands/push.py
elementalcms/management/snippetscommands/remove.py
elementalcms/management/staticcommands/__init__.py
elemental_cms-2.0.6.dist-info/METADATA
elemental_cms-2.0.6.dist-info/WHEEL
elemental_cms-2.0.6.dist-info/entry_points.txt
elemental_cms-2.0.6.dist-info/top_level.txt
elemental_cms-2.0.6.dist-info/RECORD
