Metadata-Version: 2.4
Name: elemental-cms
Version: 2.0.6
Summary: Flask + MongoDB Web CMS for Developers.
Home-page: https://github.com/paranoid-software/elemental-cms
Author: Paranoid Software
Author-email: info@paranoid.software
License: MPL-2.0
Classifier: Programming Language :: Python :: 3
Classifier: Programming Language :: Python :: 3.7
Classifier: Operating System :: OS Independent
Requires-Python: >=3.6
License-File: LICENSE
Requires-Dist: Flask==2.2.5
Requires-Dist: Werkzeug==2.2.3
Requires-Dist: Jinja2>=3.0.0
Requires-Dist: pycountry>=20.7.3
Requires-Dist: pymongo>=3.12.1
Requires-Dist: cloup>=0.13.0
Requires-Dist: deepdiff>=5.6.0
Requires-Dist: Flask-Babel==2.0.0
Requires-Dist: google-cloud-storage>=2.3.0
Requires-Dist: urllib3<2.0.0
Requires-Dist: MarkupSafe>=2.1.0
Requires-Dist: rich>=13.0.0
Dynamic: author
Dynamic: author-email
Dynamic: classifier
Dynamic: description
Dynamic: description-content-type
Dynamic: home-page
Dynamic: license
Dynamic: license-file
Dynamic: requires-dist
Dynamic: requires-python
Dynamic: summary
